caddytail/__init__.py
caddytail/__main__.py
caddytail/api.py
caddytail/bin/caddy
caddytail-0.2.0.dist-info/METADATA
caddytail-0.2.0.dist-info/WHEEL
caddytail-0.2.0.dist-info/entry_points.txt
caddytail-0.2.0.dist-info/top_level.txt
caddytail-0.2.0.dist-info/RECORD
