Metadata-Version: 2.4
Name: caddytail
Version: 0.2.0
Summary: Caddy web server with Tailscale plugin, packaged for pip installation
Author-email: Jakub Piotr Cłapa <jpc@loee.pl>
License: Apache-2.0
Project-URL: Homepage, https://github.com/jpc/caddytail
Project-URL: Repository, https://github.com/jpc/caddytail
Project-URL: Issues, https://github.com/jpc/caddytail/issues
Keywords: caddy,tailscale,web-server,reverse-proxy,vpn
Classifier: Development Status :: 4 - Beta
Classifier: Environment :: Console
Classifier: Intended Audience :: Developers
Classifier: Intended Audience :: System Administrators
Classifier: License :: OSI Approved :: Apache Software License
Classifier: Operating System :: MacOS
Classifier: Operating System :: Microsoft :: Windows
Classifier: Operating System :: POSIX :: Linux
Classifier: Programming Language :: Python :: 3
Classifier: Programming Language :: Python :: 3.8
Classifier: Programming Language :: Python :: 3.9
Classifier: Programming Language :: Python :: 3.10
Classifier: Programming Language :: Python :: 3.11
Classifier: Programming Language :: Python :: 3.12
Classifier: Topic :: Internet :: WWW/HTTP :: HTTP Servers
Classifier: Topic :: System :: Networking
Requires-Python: >=3.8
Provides-Extra: flask
Requires-Dist: flask>=2.0; extra == "flask"
Requires-Dist: werkzeug>=2.0; extra == "flask"
Provides-Extra: fastapi
Requires-Dist: fastapi>=0.68; extra == "fastapi"
Requires-Dist: uvicorn>=0.15; extra == "fastapi"
Requires-Dist: starlette>=0.14; extra == "fastapi"
Provides-Extra: all
Requires-Dist: flask>=2.0; extra == "all"
Requires-Dist: werkzeug>=2.0; extra == "all"
Requires-Dist: fastapi>=0.68; extra == "all"
Requires-Dist: uvicorn>=0.15; extra == "all"
Requires-Dist: starlette>=0.14; extra == "all"
